spakky/__init__.py
spakky/aop/__init__.py
spakky/aop/advisor.py
spakky/aop/aspect.py
spakky/aop/error.py
spakky/aop/interfaces/__init__.py
spakky/aop/interfaces/aspect.py
spakky/aop/pointcut.py
spakky/aop/post_processor.py
spakky/application/__init__.py
spakky/application/application.py
spakky/application/application_context.py
spakky/application/error.py
spakky/aspects/__init__.py
spakky/aspects/logging.py
spakky/aspects/transactional.py
spakky/core/__init__.py
spakky/core/annotation.py
spakky/core/constants.py
spakky/core/error.py
spakky/core/importing.py
spakky/core/interfaces/__init__.py
spakky/core/interfaces/cloneable.py
spakky/core/interfaces/comparable.py
spakky/core/interfaces/disposable.py
spakky/core/interfaces/equatable.py
spakky/core/interfaces/representable.py
spakky/core/metadata.py
spakky/core/mro.py
spakky/core/mutability.py
spakky/core/proxy.py
spakky/core/types.py
spakky/domain/__init__.py
spakky/domain/error.py
spakky/domain/models/__init__.py
spakky/domain/models/aggregate_root.py
spakky/domain/models/entity.py
spakky/domain/models/event.py
spakky/domain/models/value_object.py
spakky/domain/ports/__init__.py
spakky/domain/ports/error.py
spakky/domain/ports/event/__init__.py
spakky/domain/ports/event/error.py
spakky/domain/ports/event/event_consumer.py
spakky/domain/ports/event/event_publisher.py
spakky/domain/ports/external/__init__.py
spakky/domain/ports/external/error.py
spakky/domain/ports/external/proxy.py
spakky/domain/ports/persistency/__init__.py
spakky/domain/ports/persistency/error.py
spakky/domain/ports/persistency/repository.py
spakky/domain/ports/persistency/transaction.py
spakky/domain/usecases/__init__.py
spakky/domain/usecases/command.py
spakky/domain/usecases/query.py
spakky/pod/__init__.py
spakky/pod/annotations/__init__.py
spakky/pod/annotations/lazy.py
spakky/pod/annotations/order.py
spakky/pod/annotations/pod.py
spakky/pod/annotations/primary.py
spakky/pod/annotations/qualifier.py
spakky/pod/error.py
spakky/pod/inject.py
spakky_core-2.15.1.dist-info/METADATA
spakky_core-2.15.1.dist-info/WHEEL
spakky_core-2.15.1.dist-info/RECORD
