Metadata-Version: 2.3
Name: spakky-core
Version: 2.15.1
Summary: Highly abstracted Framework core to use DDD & DI/IoC & AOP & Etc...
Author: Spakky
Author-email: sejong418@icloud.com
Requires-Python: >=3.10
Classifier: Programming Language :: Python :: 3
Classifier: Programming Language :: Python :: 3.10
Classifier: Programming Language :: Python :: 3.11
Classifier: Programming Language :: Python :: 3.12
Classifier: Programming Language :: Python :: 3.13
Requires-Dist: argon2-cffi (>=23.1.0,<24.0.0)
Requires-Dist: bcrypt (>=4.2.0,<5.0.0)
Requires-Dist: pycryptodome (>=3.20.0,<4.0.0)
Requires-Dist: typing-extensions (>=4.9.0,<5.0.0)
